tpu_star/__init__.py
tpu_star/colab_utils.py
tpu_star/utils.py
tpu_star/datasets/__init__.py
tpu_star/datasets/mnist.py
tpu_star/experiment/__init__.py
tpu_star/experiment/base.py
tpu_star/experiment/metrics.py
tpu_star/experiment/torch_gpu.py
tpu_star/experiment/torch_tpu.py
tpu_star-0.0.1rc10.dist-info/LICENSE
tpu_star-0.0.1rc10.dist-info/METADATA
tpu_star-0.0.1rc10.dist-info/WHEEL
tpu_star-0.0.1rc10.dist-info/top_level.txt
tpu_star-0.0.1rc10.dist-info/RECORD
