Metadata-Version: 2.1
Name: tpu-star
Version: 0.0.1rc10
Summary: PyTorch XLA Toolkit for quickly and easy prototyping on TPU (8 cores)
Home-page: UNKNOWN
Author: Alex Shonenkov
Author-email: shonenkov@phystech.edu
License: UNKNOWN
Platform: UNKNOWN
Requires-Dist: torch (>=1.4.0)
Requires-Dist: numpy (>=1.16.5)
Requires-Dist: tqdm (>=4.27)
